ical2vdir/__init__.py
ical2vdir-2.0.0.dist-info/licenses/COPYING
ical2vdir-2.0.0.dist-info/METADATA
ical2vdir-2.0.0.dist-info/WHEEL
ical2vdir-2.0.0.dist-info/entry_points.txt
ical2vdir-2.0.0.dist-info/top_level.txt
ical2vdir-2.0.0.dist-info/RECORD
