Metadata-Version: 2.4
Name: ical2vdir
Version: 2.0.0
Summary: convert .ics file to vdir directory
Home-page: https://github.com/fphammerle/ical2vdir
Author: Fabian Peter Hammerle
Author-email: fabian@hammerle.me
License: GPLv3+
Project-URL: Changelog, https://github.com/fphammerle/ical2vdir/blob/master/CHANGELOG.md
Keywords: calendar,event,iCal,iCalendar,ics,split,sync,vdir
Classifier: Development Status :: 4 - Beta
Classifier: Intended Audience :: End Users/Desktop
Classifier: Intended Audience :: System Administrators
Classifier: License :: OSI Approved :: GNU General Public License v3 or later (GPLv3+)
Classifier: Operating System :: OS Independent
Classifier: Programming Language :: Python :: 3.10
Classifier: Programming Language :: Python :: 3.11
Classifier: Programming Language :: Python :: 3.12
Classifier: Programming Language :: Python :: 3.13
Classifier: Topic :: Utilities
Requires-Python: >=3.10
License-File: COPYING
Requires-Dist: icalendar<5,>=4
Dynamic: author
Dynamic: author-email
Dynamic: classifier
Dynamic: description
Dynamic: description-content-type
Dynamic: home-page
Dynamic: keywords
Dynamic: license
Dynamic: license-file
Dynamic: project-url
Dynamic: requires-dist
Dynamic: requires-python
Dynamic: summary
